fcn_f0/data/fcn_1953/__init__.py
fcn_f0/data/fcn_1953/weights.h5
fcn_f0_data_fcn_1953-1.0.0.dist-info/LICENSE
fcn_f0_data_fcn_1953-1.0.0.dist-info/METADATA
fcn_f0_data_fcn_1953-1.0.0.dist-info/WHEEL
fcn_f0_data_fcn_1953-1.0.0.dist-info/top_level.txt
fcn_f0_data_fcn_1953-1.0.0.dist-info/RECORD
